omega_prime_visibility/__init__.py
omega_prime_visibility-0.1.0.dist-info/METADATA
omega_prime_visibility-0.1.0.dist-info/WHEEL
omega_prime_visibility-0.1.0.dist-info/entry_points.txt
omega_prime_visibility-0.1.0.dist-info/licenses/LICENSE
omega_prime_visibility-0.1.0.dist-info/RECORD
