Metadata-Version: 2.4
Name: omega-prime-visibility
Version: 0.1.0
Summary: Omega-Prime-Visibility: Compute Visibility of Objects Polygons
Project-URL: Homepage, https://github.com/ika-rwth-aachen/omega-prime-visibility
Project-URL: Repository, https://github.com/ika-rwth-aachen/omega-prime-visibility
Author-email: ika - RWTH Aachen <michael.schuldes@ika.rwth-aachen.de>
License: MIT
License-File: LICENSE
Keywords: automated-driving,omega-prime,simulation,traffic,visibility
Classifier: License :: OSI Approved :: MIT License
Classifier: Operating System :: OS Independent
Classifier: Programming Language :: Python :: 3
Classifier: Programming Language :: Python :: 3.10
Classifier: Programming Language :: Python :: 3.11
Classifier: Programming Language :: Python :: 3.12
Classifier: Programming Language :: Python :: 3.13
Requires-Python: >=3.10
Requires-Dist: numpy
Requires-Dist: omega-prime
Requires-Dist: polars
Requires-Dist: shapely
Requires-Dist: tqdm
Requires-Dist: visilibity
Provides-Extra: test
Requires-Dist: altair; extra == 'test'
Requires-Dist: ipywidgets; extra == 'test'
Requires-Dist: nbval; extra == 'test'
Requires-Dist: pdoc3; extra == 'test'
Requires-Dist: pre-commit; extra == 'test'
Requires-Dist: pytest; extra == 'test'
Requires-Dist: pytest-codeblocks; extra == 'test'
Requires-Dist: pytest-cov; extra == 'test'
Requires-Dist: pytest-env; extra == 'test'
Requires-Dist: pytest-progress; extra == 'test'
Requires-Dist: pytest-sugar; extra == 'test'
Requires-Dist: ruff; extra == 'test'
Requires-Dist: vegafusion[embed]>=1.5.0; extra == 'test'
Requires-Dist: vl-convert-python; extra == 'test'
